odoo/addons/stock_picking_putaway_recompute/README.rst
odoo/addons/stock_picking_putaway_recompute/__init__.py
odoo/addons/stock_picking_putaway_recompute/__manifest__.py
odoo/addons/stock_picking_putaway_recompute/i18n/it.po
odoo/addons/stock_picking_putaway_recompute/i18n/stock_picking_putaway_recompute.pot
odoo/addons/stock_picking_putaway_recompute/models/__init__.py
odoo/addons/stock_picking_putaway_recompute/models/stock_move_line.py
odoo/addons/stock_picking_putaway_recompute/models/stock_picking.py
odoo/addons/stock_picking_putaway_recompute/models/stock_picking_type.py
odoo/addons/stock_picking_putaway_recompute/readme/CONFIGURE.md
odoo/addons/stock_picking_putaway_recompute/readme/CONTEXT.md
odoo/addons/stock_picking_putaway_recompute/readme/CONTRIBUTORS.md
odoo/addons/stock_picking_putaway_recompute/readme/DESCRIPTION.md
odoo/addons/stock_picking_putaway_recompute/readme/USAGE.md
odoo/addons/stock_picking_putaway_recompute/static/description/icon.png
odoo/addons/stock_picking_putaway_recompute/static/description/index.html
odoo/addons/stock_picking_putaway_recompute/tests/__init__.py
odoo/addons/stock_picking_putaway_recompute/tests/test_recompute_putaway.py
odoo/addons/stock_picking_putaway_recompute/views/stock_move_line.xml
odoo/addons/stock_picking_putaway_recompute/views/stock_picking.xml
odoo/addons/stock_picking_putaway_recompute/views/stock_picking_type.xml
odoo_addon_stock_picking_putaway_recompute-18.0.1.0.0.5.dist-info/METADATA
odoo_addon_stock_picking_putaway_recompute-18.0.1.0.0.5.dist-info/WHEEL
odoo_addon_stock_picking_putaway_recompute-18.0.1.0.0.5.dist-info/top_level.txt
odoo_addon_stock_picking_putaway_recompute-18.0.1.0.0.5.dist-info/RECORD
